calmap/__init__.py
calmap-0.0.11.dist-info/AUTHORS.rst
calmap-0.0.11.dist-info/LICENSE.rst
calmap-0.0.11.dist-info/METADATA
calmap-0.0.11.dist-info/WHEEL
calmap-0.0.11.dist-info/top_level.txt
calmap-0.0.11.dist-info/RECORD
