Metadata-Version: 2.1
Name: calmap
Version: 0.0.11
Summary: Calendar heatmaps from Pandas time series data
Home-page: https://github.com/MarvinT/calmap
Author: Marvin Thielk; Martijn Vermaat
Author-email: marvin.thielk@gmail.com, martijn@vermaat.name
License: MIT License
Platform: any
Classifier: Development Status :: 3 - Alpha
Classifier: Intended Audience :: Developers
Classifier: Intended Audience :: Science/Research
Classifier: Operating System :: OS Independent
Classifier: Programming Language :: Python
Classifier: Programming Language :: Python :: 3
Classifier: Programming Language :: Python :: 3.6
Classifier: Programming Language :: Python :: 3.7
Classifier: Programming Language :: Python :: 3.8
Classifier: Topic :: Scientific/Engineering
License-File: LICENSE.rst
License-File: AUTHORS.rst
